euno/__init__.py
euno/api.py
euno/auth.py
euno/cli.py
euno/config.py
euno/core.py
euno/metadata_tags.py
euno/resources.py
euno/version.py
euno-0.4.0.dist-info/licenses/LICENSE
euno-0.4.0.dist-info/METADATA
euno-0.4.0.dist-info/WHEEL
euno-0.4.0.dist-info/entry_points.txt
euno-0.4.0.dist-info/top_level.txt
euno-0.4.0.dist-info/RECORD
