Metadata-Version: 2.4
Name: euno
Version: 0.4.0
Summary: Euno's CLI library to programmatically interact with Euno instance
Home-page: https://github.com/euno-ai/euno-sdk
Author: Euno Team
Author-email: Euno Team <team@euno.ai>
Maintainer-email: Euno Team <team@euno.ai>
License: MIT
Project-URL: Homepage, https://github.com/euno-ai/euno-sdk
Project-URL: Documentation, https://github.com/euno-ai/euno-sdk#readme
Project-URL: Repository, https://github.com/euno-ai/euno-sdk.git
Project-URL: Issues, https://github.com/euno-ai/euno-sdk/issues
Keywords: euno,sdk,cli,api
Classifier: Development Status :: 3 - Alpha
Classifier: Intended Audience :: Developers
Classifier: License :: OSI Approved :: MIT License
Classifier: Operating System :: OS Independent
Classifier: Programming Language :: Python :: 3
Classifier: Programming Language :: Python :: 3.8
Classifier: Programming Language :: Python :: 3.9
Classifier: Programming Language :: Python :: 3.10
Classifier: Programming Language :: Python :: 3.11
Classifier: Programming Language :: Python :: 3.12
Classifier: Topic :: Software Development :: Libraries :: Python Modules
Classifier: Topic :: System :: Systems Administration
Requires-Python: >=3.8
License-File: LICENSE
Requires-Dist: click>=8.0.0
Requires-Dist: requests>=2.25.0
Requires-Dist: pydantic>=1.8.0
Provides-Extra: dev
Requires-Dist: pytest>=6.0.0; extra == "dev"
Requires-Dist: pytest-cov>=2.0.0; extra == "dev"
Requires-Dist: black>=21.0.0; extra == "dev"
Requires-Dist: flake8>=3.8.0; extra == "dev"
Requires-Dist: mypy>=0.800; extra == "dev"
Requires-Dist: pre-commit>=2.0.0; extra == "dev"
Requires-Dist: types-requests>=2.25.0; extra == "dev"
Dynamic: author
Dynamic: home-page
Dynamic: license-file
Dynamic: requires-python
